<items>
 
<item>
<title>[COLOR=gold]|~~~~~~~~~~[B]A Selection of Radio Streams[/B]~~~~~~~~~~|[/COLOR]</title>
<link></link>
<thumbnail>http://www.fullhdwpp.com/wp-content/uploads/Boombox_www.FullHDWpp.com_.jpg?x69613</thumbnail>
</item>
 
<item>
<title>[COLOR=gold][B]DI.FM[/B][/COLOR] Addictive Electronic Music >></title>
<link>https://raw.githubusercontent.com/alfreddempsey3/repository.rage/master/xml/DI.xml</link>
<thumbnail>http://www.androidpolice.com/wp-content/uploads/2014/05/nexusae0_unnamed-114.png</thumbnail>
</item>

<item>
<title>[COLOR=gold][B]SOMA FM[/B][/COLOR] Commercial Free Radio Stations >></title>
<link>https://raw.githubusercontent.com/alfreddempsey3/repository.rage/master/xml/soma.xml</link>
<thumbnail>https://images-na.ssl-images-amazon.com/images/I/71LFaSQE2aL.png</thumbnail>
</item>
   
<item>
<title>[COLOR=gold][B]RTE Radio Stations[/B][/COLOR] Irish National Broadcaster >></title>
<link>https://raw.githubusercontent.com/alfreddempsey3/repository.rage/master/xml/rte.xml</link>
<thumbnail>http://www.1zoom.net/big2/576/329088-alexfas01.jpg</thumbnail>
</item>

<item>
<title>[COLOR=gold][B]BBC Radio Stations[/B][/COLOR] British Broadcasting Corporation >></title>
<link>https://raw.githubusercontent.com/alfreddempsey3/repository.rage/master/xml/bbc.xml</link>
<thumbnail>http://wallpapercave.com/wp/aSBulKM.jpg</thumbnail>
</item>

<item>
<title>[COLOR=gold][B]Various Internet Radio Stations[/B][/COLOR] Different musical genres >></title>
<link>https://raw.githubusercontent.com/alfreddempsey3/repository.rage/master/xml/Various.xml</link>
<thumbnail>http://www.listenfmradios.com/wp-content/uploads/2015/04/Delima-FM-Samarinda-Logo.jpg</thumbnail>
</item>
 
<items>
